bump4version/__init__.py
bump4version/__main__.py
bump4version/cli.py
bump4version/exceptions.py
bump4version/functions.py
bump4version/utils.py
bump4version/vcs.py
bump4version/version_part.py
bump4version-1.0.0.dev3.dist-info/LICENSE.rst
bump4version-1.0.0.dev3.dist-info/METADATA
bump4version-1.0.0.dev3.dist-info/WHEEL
bump4version-1.0.0.dev3.dist-info/entry_points.txt
bump4version-1.0.0.dev3.dist-info/top_level.txt
bump4version-1.0.0.dev3.dist-info/RECORD
