Metadata-Version: 2.1
Name: bump4version
Version: 1.0.0.dev3
Summary: A CLI tool for managing source code version information
Author-email: Christian Verkerk <christianverkerk@ymail.com>
License: MIT
Project-URL: Homepage, https://github.com/olutra/bump4version
Classifier: Development Status :: 4 - Beta
Classifier: Intended Audience :: Developers
Classifier: License :: OSI Approved :: MIT License
Classifier: Operating System :: OS Independent
Classifier: Programming Language :: Python
Classifier: Programming Language :: Python :: 3
Classifier: Programming Language :: Python :: 3.8
Classifier: Programming Language :: Python :: 3.9
Classifier: Programming Language :: Python :: 3.10
Classifier: Programming Language :: Python :: 3.11
Classifier: Programming Language :: Python :: 3.12
Classifier: Programming Language :: Python :: 3.13
Classifier: Programming Language :: Python :: 3 :: Only
Classifier: Programming Language :: Python :: Implementation :: PyPy
Requires-Python: >=3.8
License-File: LICENSE.rst
Provides-Extra: test
Requires-Dist: testfixtures >=7.1.0 ; extra == 'test'
Requires-Dist: pytest >=7.3.1 ; extra == 'test'
Requires-Dist: pytest-xdist >=3.2.1 ; extra == 'test'
